huggingface_hub/__init__.py
huggingface_hub/_commit_api.py
huggingface_hub/_commit_scheduler.py
huggingface_hub/_inference_endpoints.py
huggingface_hub/_local_folder.py
huggingface_hub/_login.py
huggingface_hub/_oauth.py
huggingface_hub/_snapshot_download.py
huggingface_hub/_space_api.py
huggingface_hub/_tensorboard_logger.py
huggingface_hub/_upload_large_folder.py
huggingface_hub/_webhooks_payload.py
huggingface_hub/_webhooks_server.py
huggingface_hub/community.py
huggingface_hub/constants.py
huggingface_hub/dataclasses.py
huggingface_hub/errors.py
huggingface_hub/fastai_utils.py
huggingface_hub/file_download.py
huggingface_hub/hf_api.py
huggingface_hub/hf_file_system.py
huggingface_hub/hub_mixin.py
huggingface_hub/inference_api.py
huggingface_hub/keras_mixin.py
huggingface_hub/lfs.py
huggingface_hub/py.typed
huggingface_hub/repocard.py
huggingface_hub/repocard_data.py
huggingface_hub/repository.py
huggingface_hub/commands/__init__.py
huggingface_hub/commands/_cli_utils.py
huggingface_hub/commands/delete_cache.py
huggingface_hub/commands/download.py
huggingface_hub/commands/env.py
huggingface_hub/commands/huggingface_cli.py
huggingface_hub/commands/lfs.py
huggingface_hub/commands/repo.py
huggingface_hub/commands/repo_files.py
huggingface_hub/commands/scan_cache.py
huggingface_hub/commands/tag.py
huggingface_hub/commands/upload.py
huggingface_hub/commands/upload_large_folder.py
huggingface_hub/commands/user.py
huggingface_hub/commands/version.py
huggingface_hub/inference/__init__.py
huggingface_hub/inference/_client.py
huggingface_hub/inference/_common.py
huggingface_hub/inference/_generated/__init__.py
huggingface_hub/inference/_generated/_async_client.py
huggingface_hub/inference/_generated/types/__init__.py
huggingface_hub/inference/_generated/types/audio_classification.py
huggingface_hub/inference/_generated/types/audio_to_audio.py
huggingface_hub/inference/_generated/types/automatic_speech_recognition.py
huggingface_hub/inference/_generated/types/base.py
huggingface_hub_gomall-0.33.0.dev0.dist-info/licenses/LICENSE
huggingface_hub_gomall-0.33.0.dev0.dist-info/METADATA
huggingface_hub_gomall-0.33.0.dev0.dist-info/WHEEL
huggingface_hub_gomall-0.33.0.dev0.dist-info/entry_points.txt
huggingface_hub_gomall-0.33.0.dev0.dist-info/top_level.txt
huggingface_hub_gomall-0.33.0.dev0.dist-info/RECORD
